nmk_python/__init__.py
nmk_python/badges.yml
nmk_python/build.py
nmk_python/build.yml
nmk_python/doc.yml
nmk_python/files.py
nmk_python/files.yml
nmk_python/plugin.yml
nmk_python/project.yml
nmk_python/ruff.py
nmk_python/ruff.yml
nmk_python/tests.py
nmk_python/tests.yml
nmk_python/version.py
nmk_python/version.yml
nmk_python/backends/__init__.py
nmk_python/backends/build_backend.py
nmk_python/backends/factory.py
nmk_python/backends/pip_build_backend.py
nmk_python/backends/uv_build_backend.py
nmk_python/templates/__init__.py
nmk_python/templates/build.toml.jinja
nmk_python/templates/pytest.toml.jinja
nmk_python/templates/python-settings.json.jinja
nmk_python/templates/python-test-debug-launch.json.jinja
nmk_python/templates/ruff.toml.jinja
nmk_python-1.8.1.dist-info/licenses/LICENSE
nmk_python-1.8.1.dist-info/METADATA
nmk_python-1.8.1.dist-info/WHEEL
nmk_python-1.8.1.dist-info/top_level.txt
nmk_python-1.8.1.dist-info/RECORD
