Metadata-Version: 2.4
Name: nmk-python
Version: 1.8.1
Summary: Python plugin for nmk build system
Author: The dynod project
Maintainer: The dynod project
License: MIT License
Project-URL: Homepage, https://github.com/dynod/nmk-python
Project-URL: Repository, https://github.com/dynod/nmk-python
Project-URL: Issues, https://github.com/dynod/nmk/issues?q=is%3Aopen+is%3Aissue+label%3Aplugin%3Apython
Classifier: Programming Language :: Python :: 3.10
Classifier: Programming Language :: Python :: 3.11
Classifier: Programming Language :: Python :: 3.12
Classifier: Programming Language :: Python :: 3.13
Classifier: Programming Language :: Python :: 3.14
Requires-Python: >=3.10
License-File: LICENSE
Requires-Dist: nmk-base>=1.0.1
Requires-Dist: Jinja2
Requires-Dist: tomlkit
Requires-Dist: setuptools
Requires-Dist: wheel
Requires-Dist: build
Requires-Dist: ruff
Requires-Dist: pytest-xdist
Requires-Dist: pytest-cov
Requires-Dist: pytest-multilog
Dynamic: license-file
